sendlix/__init__.py
sendlix/_compat.py
sendlix/auth.py
sendlix/constants.py
sendlix/clients/__init__.py
sendlix/clients/_helpers.py
sendlix/clients/client.py
sendlix/clients/email_client.py
sendlix/clients/group_client.py
sendlix/proto/EmailData_pb2.py
sendlix/proto/EmailData_pb2_grpc.py
sendlix/proto/auth_pb2.py
sendlix/proto/auth_pb2_grpc.py
sendlix/proto/email_pb2.py
sendlix/proto/email_pb2_grpc.py
sendlix/proto/group_pb2.py
sendlix/proto/group_pb2_grpc.py
sendlix-1.0.0.dist-info/licenses/LICENSE
sendlix-1.0.0.dist-info/METADATA
sendlix-1.0.0.dist-info/WHEEL
sendlix-1.0.0.dist-info/top_level.txt
sendlix-1.0.0.dist-info/RECORD
