Metadata-Version: 2.4
Name: sendlix
Version: 1.0.0
Summary: Python SDK for the Sendlix gRPC API
Author: Sendlix
License-Expression: Apache-2.0
Keywords: grpc,email,sdk,sendlix
Requires-Python: >=3.9
License-File: LICENSE
Requires-Dist: grpcio>=1.71.0
Requires-Dist: protobuf>=5.29.0
Requires-Dist: typing-extensions>=4.12
Provides-Extra: dev
Requires-Dist: pytest>=8.3; extra == "dev"
Requires-Dist: grpcio-tools>=1.71.0; extra == "dev"
Dynamic: license-file
